agori/__init__.py
agori/core/__init__.py
agori/core/base.py
agori/core/db.py
agori/decision_frameworks/__init__.py
agori/decision_frameworks/ngt/__init__.py
agori/decision_frameworks/ngt/exceptions.py
agori/decision_frameworks/ngt/models.py
agori/decision_frameworks/ngt/processor.py
agori/decision_frameworks/ngt/prompts.py
agori/hr/models.py
agori/hr/hiring/__init__.py
agori/hr/hiring/screening.py
agori/utils/__init__.py
agori/utils/exceptions.py
agori-0.1.4.dist-info/METADATA
agori-0.1.4.dist-info/WHEEL
agori-0.1.4.dist-info/licenses/LICENSE
agori-0.1.4.dist-info/RECORD
