Metadata-Version: 2.3
Name: agori
Version: 0.1.4
Summary: AI-powered decision-making frameworks for enhancing group decisions
Project-URL: Homepage, https://github.com/govindshukl/agori
Project-URL: Bug Tracker, https://github.com/govindshukl/agori/issues
Project-URL: Repository, https://github.com/govindshukl/agori.git
Project-URL: Documentation, https://github.com/govindshukl/agori#readme
Author-email: Govind Shukla <govind.shukl@gmail.com>
Keywords: ai-frameworks,artificial-intelligence,azure-openai,collaborative-decision-making,decision-making,group-decision,langchain,nominal-group-technique
Requires-Python: >=3.8
Requires-Dist: chromadb
Requires-Dist: cryptography
Requires-Dist: langchain
Requires-Dist: langchain-community
Requires-Dist: langchain-core
Requires-Dist: langchain-openai
Requires-Dist: numpy
Requires-Dist: pandas
Requires-Dist: pypdf
Requires-Dist: pytest-asyncio
Requires-Dist: python-dotenv
Requires-Dist: tenacity
Requires-Dist: tiktoken
Provides-Extra: docs
Requires-Dist: mkdocs-material>=9.0.0; extra == 'docs'
Requires-Dist: mkdocs>=1.4.0; extra == 'docs'
Requires-Dist: mkdocstrings>=0.20.0; extra == 'docs'
Provides-Extra: test
Requires-Dist: black>=23.0.0; extra == 'test'
Requires-Dist: flake8>=6.0.0; extra == 'test'
Requires-Dist: mypy>=1.0.0; extra == 'test'
Requires-Dist: pytest-cov>=4.0.0; extra == 'test'
Requires-Dist: pytest-mock>=3.10.0; extra == 'test'
Requires-Dist: pytest>=7.0.0; extra == 'test'
Requires-Dist: types-requests>=2.0.0; extra == 'test'
